{
  "s2": [
    {
      "q": "Antepartum hemorrhage is defined as bleeding from the vagina:",
      "options": [
        "At any time during pregnancy",
        "After 20 weeks of pregnancy and before childbirth",
        "Only in the third trimester",
        "Before 20 weeks of pregnancy"
      ],
      "correct": 1,
      "explain": "APH is defined as bleeding from the vagina occurring at any time after the 20th week of pregnancy and before childbirth. Bleeding before 20 weeks is classified as threatened/missed/inevitable abortion."
    },
    {
      "q": "When assessing this aspect, the most important factor is:",
      "options": [
        "Clinical correlation with patient presentation",
        "Laboratory confirmation",
        "Imaging evidence",
        "All of the above together"
      ],
      "correct": 3,
      "explain": "Assessment requires integration of clinical, laboratory, and imaging findings."
    },
    {
      "q": "The incidence of this condition is highest in which population?",
      "options": [
        "Primigravidas",
        "Multiparous women",
        "Women aged 35+ years",
        "Depends on the specific condition and risk factors"
      ],
      "correct": 3,
      "explain": "Incidence varies by condition — each has its own epidemiology and risk profile."
    },
    {
      "q": "The clinical significance of this section is:",
      "options": [
        "It guides management decisions",
        "It is primarily theoretical",
        "It applies only to research settings",
        "It has limited clinical utility"
      ],
      "correct": 0,
      "explain": "Understanding these concepts directly informs clinical management."
    },
    {
      "q": "In obstetric practice, this knowledge helps:",
      "options": [
        "Predict and prevent complications",
        "Diagnose conditions early",
        "Choose appropriate management",
        "All of the above"
      ],
      "correct": 3,
      "explain": "Comprehensive knowledge enables prevention, early diagnosis, and optimal management."
    }
  ],
  "s3": [
    {
      "q": "The clinical significance of this section is:",
      "options": [
        "It guides management decisions",
        "It is primarily theoretical",
        "It applies only to research settings",
        "It has limited clinical utility"
      ],
      "correct": 0,
      "explain": "Understanding these concepts directly informs clinical management."
    },
    {
      "q": "The etiology of this condition involves:",
      "options": [
        "Genetic factors alone",
        "Environmental factors alone",
        "A complex interplay of genetic, environmental, and multifactorial elements",
        "Iatrogenic causes only"
      ],
      "correct": 2,
      "explain": "Most obstetric conditions have multifactorial etiology."
    },
    {
      "q": "Which of the following is a key concept?",
      "options": [
        "It is essential for understanding the condition",
        "It is rarely relevant in clinical practice",
        "It applies only to specific populations",
        "It has been replaced by newer classifications"
      ],
      "correct": 0,
      "explain": "Understanding key concepts is fundamental to clinical management."
    },
    {
      "q": "In obstetric practice, this knowledge helps:",
      "options": [
        "Predict and prevent complications",
        "Diagnose conditions early",
        "Choose appropriate management",
        "All of the above"
      ],
      "correct": 3,
      "explain": "Comprehensive knowledge enables prevention, early diagnosis, and optimal management."
    },
    {
      "q": "Which of the following is a known risk factor?",
      "options": [
        "Maternal age above 35",
        "Multiparity",
        "Previous similar history",
        "All of the above may contribute depending on the condition"
      ],
      "correct": 3,
      "explain": "Multiple risk factors often contribute to obstetric conditions."
    }
  ],
  "s4": [
    {
      "q": "When assessing this aspect, the most important factor is:",
      "options": [
        "Clinical correlation with patient presentation",
        "Laboratory confirmation",
        "Imaging evidence",
        "All of the above together"
      ],
      "correct": 3,
      "explain": "Assessment requires integration of clinical, laboratory, and imaging findings."
    },
    {
      "q": "Which of the following best defines this condition?",
      "options": [
        "A pathological deviation from normal anatomy or function",
        "A condition requiring surgical intervention",
        "An incidental finding with no clinical significance",
        "A self-limiting disorder of pregnancy"
      ],
      "correct": 0,
      "explain": "A definition describes the essential nature of a condition as a deviation from normal."
    },
    {
      "q": "Which of the following is a key concept?",
      "options": [
        "It is essential for understanding the condition",
        "It is rarely relevant in clinical practice",
        "It applies only to specific populations",
        "It has been replaced by newer classifications"
      ],
      "correct": 0,
      "explain": "Understanding key concepts is fundamental to clinical management."
    },
    {
      "q": "The clinical significance of this section is:",
      "options": [
        "It guides management decisions",
        "It is primarily theoretical",
        "It applies only to research settings",
        "It has limited clinical utility"
      ],
      "correct": 0,
      "explain": "Understanding these concepts directly informs clinical management."
    },
    {
      "q": "The incidence of this condition is highest in which population?",
      "options": [
        "Primigravidas",
        "Multiparous women",
        "Women aged 35+ years",
        "Depends on the specific condition and risk factors"
      ],
      "correct": 3,
      "explain": "Incidence varies by condition — each has its own epidemiology and risk profile."
    }
  ],
  "s5": [
    {
      "q": "Which of the following is a key concept?",
      "options": [
        "It is essential for understanding the condition",
        "It is rarely relevant in clinical practice",
        "It applies only to specific populations",
        "It has been replaced by newer classifications"
      ],
      "correct": 0,
      "explain": "Understanding key concepts is fundamental to clinical management."
    },
    {
      "q": "When assessing this aspect, the most important factor is:",
      "options": [
        "Clinical correlation with patient presentation",
        "Laboratory confirmation",
        "Imaging evidence",
        "All of the above together"
      ],
      "correct": 3,
      "explain": "Assessment requires integration of clinical, laboratory, and imaging findings."
    },
    {
      "q": "In obstetric practice, this knowledge helps:",
      "options": [
        "Predict and prevent complications",
        "Diagnose conditions early",
        "Choose appropriate management",
        "All of the above"
      ],
      "correct": 3,
      "explain": "Comprehensive knowledge enables prevention, early diagnosis, and optimal management."
    },
    {
      "q": "The clinical significance of this section is:",
      "options": [
        "It guides management decisions",
        "It is primarily theoretical",
        "It applies only to research settings",
        "It has limited clinical utility"
      ],
      "correct": 0,
      "explain": "Understanding these concepts directly informs clinical management."
    },
    {
      "q": "The most common type is:",
      "options": [
        "Type 1 — mild form",
        "Type 2 — moderate form",
        "Type 3 — severe form",
        "Depends on the specific condition and classification system"
      ],
      "correct": 3,
      "explain": "Classification varies by condition — each has its own typing system."
    }
  ],
  "s6": [
    {
      "q": "Which sign on examination is characteristic?",
      "options": [
        "Abnormal vital signs",
        "Palpable abdominal mass",
        "Specific findings vary by condition",
        "None of the above"
      ],
      "correct": 2,
      "explain": "Examination findings depend heavily on the specific obstetric condition."
    },
    {
      "q": "The most common presenting symptom is:",
      "options": [
        "Pain",
        "Abnormal bleeding",
        "Both pain and abnormal bleeding",
        "Depends on the specific condition"
      ],
      "correct": 3,
      "explain": "Clinical presentation varies — pain and bleeding are common but not universal symptoms."
    },
    {
      "q": "The clinical significance of this section is:",
      "options": [
        "It guides management decisions",
        "It is primarily theoretical",
        "It applies only to research settings",
        "It has limited clinical utility"
      ],
      "correct": 0,
      "explain": "Understanding these concepts directly informs clinical management."
    },
    {
      "q": "Which of the following is a key concept?",
      "options": [
        "It is essential for understanding the condition",
        "It is rarely relevant in clinical practice",
        "It applies only to specific populations",
        "It has been replaced by newer classifications"
      ],
      "correct": 0,
      "explain": "Understanding key concepts is fundamental to clinical management."
    },
    {
      "q": "In obstetric practice, this knowledge helps:",
      "options": [
        "Predict and prevent complications",
        "Diagnose conditions early",
        "Choose appropriate management",
        "All of the above"
      ],
      "correct": 3,
      "explain": "Comprehensive knowledge enables prevention, early diagnosis, and optimal management."
    }
  ],
  "s7": [
    {
      "q": "Which of the following is a key concept?",
      "options": [
        "It is essential for understanding the condition",
        "It is rarely relevant in clinical practice",
        "It applies only to specific populations",
        "It has been replaced by newer classifications"
      ],
      "correct": 0,
      "explain": "Understanding key concepts is fundamental to clinical management."
    },
    {
      "q": "The first-line investigation is:",
      "options": [
        "Ultrasound",
        "Complete blood count",
        "Urine analysis",
        "Depends on the clinical suspicion"
      ],
      "correct": 3,
      "explain": "Choice of investigation depends on the suspected condition."
    },
    {
      "q": "Which laboratory test is most relevant?",
      "options": [
        "Hemoglobin level",
        "Coagulation profile",
        "Specific test depends on the condition being investigated",
        "All of the above should be checked routinely"
      ],
      "correct": 2,
      "explain": "Investigations are guided by clinical suspicion and differential diagnosis."
    },
    {
      "q": "In obstetric practice, this knowledge helps:",
      "options": [
        "Predict and prevent complications",
        "Diagnose conditions early",
        "Choose appropriate management",
        "All of the above"
      ],
      "correct": 3,
      "explain": "Comprehensive knowledge enables prevention, early diagnosis, and optimal management."
    },
    {
      "q": "When assessing this aspect, the most important factor is:",
      "options": [
        "Clinical correlation with patient presentation",
        "Laboratory confirmation",
        "Imaging evidence",
        "All of the above together"
      ],
      "correct": 3,
      "explain": "Assessment requires integration of clinical, laboratory, and imaging findings."
    }
  ],
  "s8": [
    {
      "q": "When assessing this aspect, the most important factor is:",
      "options": [
        "Clinical correlation with patient presentation",
        "Laboratory confirmation",
        "Imaging evidence",
        "All of the above together"
      ],
      "correct": 3,
      "explain": "Assessment requires integration of clinical, laboratory, and imaging findings."
    },
    {
      "q": "In obstetric practice, this knowledge helps:",
      "options": [
        "Predict and prevent complications",
        "Diagnose conditions early",
        "Choose appropriate management",
        "All of the above"
      ],
      "correct": 3,
      "explain": "Comprehensive knowledge enables prevention, early diagnosis, and optimal management."
    },
    {
      "q": "Which of the following is a key concept?",
      "options": [
        "It is essential for understanding the condition",
        "It is rarely relevant in clinical practice",
        "It applies only to specific populations",
        "It has been replaced by newer classifications"
      ],
      "correct": 0,
      "explain": "Understanding key concepts is fundamental to clinical management."
    },
    {
      "q": "First-line management consists of:",
      "options": [
        "Immediate surgical intervention",
        "Conservative/medical management",
        "Referral to a specialist",
        "Depends on the specific condition and severity"
      ],
      "correct": 3,
      "explain": "Management approach varies — some conditions require surgery, others medical or conservative care."
    },
    {
      "q": "Which factor most influences the choice of treatment?",
      "options": [
        "Gestational age at presentation",
        "Maternal preference",
        "Facility resources",
        "All of the above — treatment is individualized"
      ],
      "correct": 3,
      "explain": "Obstetric management is tailored to gestational age, maternal status, and available resources."
    }
  ],
  "s9": [
    {
      "q": "Which of the following best defines this condition?",
      "options": [
        "A pathological deviation from normal anatomy or function",
        "A condition requiring surgical intervention",
        "An incidental finding with no clinical significance",
        "A self-limiting disorder of pregnancy"
      ],
      "correct": 0,
      "explain": "A definition describes the essential nature of a condition as a deviation from normal."
    },
    {
      "q": "Which of the following is a key concept?",
      "options": [
        "It is essential for understanding the condition",
        "It is rarely relevant in clinical practice",
        "It applies only to specific populations",
        "It has been replaced by newer classifications"
      ],
      "correct": 0,
      "explain": "Understanding key concepts is fundamental to clinical management."
    },
    {
      "q": "In obstetric practice, this knowledge helps:",
      "options": [
        "Predict and prevent complications",
        "Diagnose conditions early",
        "Choose appropriate management",
        "All of the above"
      ],
      "correct": 3,
      "explain": "Comprehensive knowledge enables prevention, early diagnosis, and optimal management."
    },
    {
      "q": "When assessing this aspect, the most important factor is:",
      "options": [
        "Clinical correlation with patient presentation",
        "Laboratory confirmation",
        "Imaging evidence",
        "All of the above together"
      ],
      "correct": 3,
      "explain": "Assessment requires integration of clinical, laboratory, and imaging findings."
    },
    {
      "q": "The clinical significance of this section is:",
      "options": [
        "It guides management decisions",
        "It is primarily theoretical",
        "It applies only to research settings",
        "It has limited clinical utility"
      ],
      "correct": 0,
      "explain": "Understanding these concepts directly informs clinical management."
    }
  ],
  "s10": [
    {
      "q": "In obstetric practice, this knowledge helps:",
      "options": [
        "Predict and prevent complications",
        "Diagnose conditions early",
        "Choose appropriate management",
        "All of the above"
      ],
      "correct": 3,
      "explain": "Comprehensive knowledge enables prevention, early diagnosis, and optimal management."
    },
    {
      "q": "Which of the following is a known risk factor?",
      "options": [
        "Maternal age above 35",
        "Multiparity",
        "Previous similar history",
        "All of the above may contribute depending on the condition"
      ],
      "correct": 3,
      "explain": "Multiple risk factors often contribute to obstetric conditions."
    },
    {
      "q": "When assessing this aspect, the most important factor is:",
      "options": [
        "Clinical correlation with patient presentation",
        "Laboratory confirmation",
        "Imaging evidence",
        "All of the above together"
      ],
      "correct": 3,
      "explain": "Assessment requires integration of clinical, laboratory, and imaging findings."
    },
    {
      "q": "The etiology of this condition involves:",
      "options": [
        "Genetic factors alone",
        "Environmental factors alone",
        "A complex interplay of genetic, environmental, and multifactorial elements",
        "Iatrogenic causes only"
      ],
      "correct": 2,
      "explain": "Most obstetric conditions have multifactorial etiology."
    },
    {
      "q": "The clinical significance of this section is:",
      "options": [
        "It guides management decisions",
        "It is primarily theoretical",
        "It applies only to research settings",
        "It has limited clinical utility"
      ],
      "correct": 0,
      "explain": "Understanding these concepts directly informs clinical management."
    }
  ],
  "s11": [
    {
      "q": "The clinical significance of this section is:",
      "options": [
        "It guides management decisions",
        "It is primarily theoretical",
        "It applies only to research settings",
        "It has limited clinical utility"
      ],
      "correct": 0,
      "explain": "Understanding these concepts directly informs clinical management."
    },
    {
      "q": "In obstetric practice, this knowledge helps:",
      "options": [
        "Predict and prevent complications",
        "Diagnose conditions early",
        "Choose appropriate management",
        "All of the above"
      ],
      "correct": 3,
      "explain": "Comprehensive knowledge enables prevention, early diagnosis, and optimal management."
    },
    {
      "q": "The most common presenting symptom is:",
      "options": [
        "Pain",
        "Abnormal bleeding",
        "Both pain and abnormal bleeding",
        "Depends on the specific condition"
      ],
      "correct": 3,
      "explain": "Clinical presentation varies — pain and bleeding are common but not universal symptoms."
    },
    {
      "q": "Which of the following is a key concept?",
      "options": [
        "It is essential for understanding the condition",
        "It is rarely relevant in clinical practice",
        "It applies only to specific populations",
        "It has been replaced by newer classifications"
      ],
      "correct": 0,
      "explain": "Understanding key concepts is fundamental to clinical management."
    },
    {
      "q": "Which sign on examination is characteristic?",
      "options": [
        "Abnormal vital signs",
        "Palpable abdominal mass",
        "Specific findings vary by condition",
        "None of the above"
      ],
      "correct": 2,
      "explain": "Examination findings depend heavily on the specific obstetric condition."
    }
  ],
  "s12": [
    {
      "q": "Which of the following is a key concept?",
      "options": [
        "It is essential for understanding the condition",
        "It is rarely relevant in clinical practice",
        "It applies only to specific populations",
        "It has been replaced by newer classifications"
      ],
      "correct": 0,
      "explain": "Understanding key concepts is fundamental to clinical management."
    },
    {
      "q": "The first-line investigation is:",
      "options": [
        "Ultrasound",
        "Complete blood count",
        "Urine analysis",
        "Depends on the clinical suspicion"
      ],
      "correct": 3,
      "explain": "Choice of investigation depends on the suspected condition."
    },
    {
      "q": "The clinical significance of this section is:",
      "options": [
        "It guides management decisions",
        "It is primarily theoretical",
        "It applies only to research settings",
        "It has limited clinical utility"
      ],
      "correct": 0,
      "explain": "Understanding these concepts directly informs clinical management."
    },
    {
      "q": "Which laboratory test is most relevant?",
      "options": [
        "Hemoglobin level",
        "Coagulation profile",
        "Specific test depends on the condition being investigated",
        "All of the above should be checked routinely"
      ],
      "correct": 2,
      "explain": "Investigations are guided by clinical suspicion and differential diagnosis."
    },
    {
      "q": "When assessing this aspect, the most important factor is:",
      "options": [
        "Clinical correlation with patient presentation",
        "Laboratory confirmation",
        "Imaging evidence",
        "All of the above together"
      ],
      "correct": 3,
      "explain": "Assessment requires integration of clinical, laboratory, and imaging findings."
    }
  ],
  "s13": [
    {
      "q": "When assessing this aspect, the most important factor is:",
      "options": [
        "Clinical correlation with patient presentation",
        "Laboratory confirmation",
        "Imaging evidence",
        "All of the above together"
      ],
      "correct": 3,
      "explain": "Assessment requires integration of clinical, laboratory, and imaging findings."
    },
    {
      "q": "The clinical significance of this section is:",
      "options": [
        "It guides management decisions",
        "It is primarily theoretical",
        "It applies only to research settings",
        "It has limited clinical utility"
      ],
      "correct": 0,
      "explain": "Understanding these concepts directly informs clinical management."
    },
    {
      "q": "A potential maternal complication includes:",
      "options": [
        "Hemorrhage",
        "Infection",
        "Thromboembolism",
        "All of the above are possible"
      ],
      "correct": 3,
      "explain": "Obstetric conditions can lead to hemorrhage, infection, thromboembolism, and other complications."
    },
    {
      "q": "Which of the following is a key concept?",
      "options": [
        "It is essential for understanding the condition",
        "It is rarely relevant in clinical practice",
        "It applies only to specific populations",
        "It has been replaced by newer classifications"
      ],
      "correct": 0,
      "explain": "Understanding key concepts is fundamental to clinical management."
    },
    {
      "q": "In obstetric practice, this knowledge helps:",
      "options": [
        "Predict and prevent complications",
        "Diagnose conditions early",
        "Choose appropriate management",
        "All of the above"
      ],
      "correct": 3,
      "explain": "Comprehensive knowledge enables prevention, early diagnosis, and optimal management."
    }
  ],
  "s14": [
    {
      "q": "When assessing this aspect, the most important factor is:",
      "options": [
        "Clinical correlation with patient presentation",
        "Laboratory confirmation",
        "Imaging evidence",
        "All of the above together"
      ],
      "correct": 3,
      "explain": "Assessment requires integration of clinical, laboratory, and imaging findings."
    },
    {
      "q": "The clinical significance of this section is:",
      "options": [
        "It guides management decisions",
        "It is primarily theoretical",
        "It applies only to research settings",
        "It has limited clinical utility"
      ],
      "correct": 0,
      "explain": "Understanding these concepts directly informs clinical management."
    },
    {
      "q": "In obstetric practice, this knowledge helps:",
      "options": [
        "Predict and prevent complications",
        "Diagnose conditions early",
        "Choose appropriate management",
        "All of the above"
      ],
      "correct": 3,
      "explain": "Comprehensive knowledge enables prevention, early diagnosis, and optimal management."
    },
    {
      "q": "Which of the following is a key concept?",
      "options": [
        "It is essential for understanding the condition",
        "It is rarely relevant in clinical practice",
        "It applies only to specific populations",
        "It has been replaced by newer classifications"
      ],
      "correct": 0,
      "explain": "Understanding key concepts is fundamental to clinical management."
    },
    {
      "q": "Which factor most influences the choice of treatment?",
      "options": [
        "Gestational age at presentation",
        "Maternal preference",
        "Facility resources",
        "All of the above — treatment is individualized"
      ],
      "correct": 3,
      "explain": "Obstetric management is tailored to gestational age, maternal status, and available resources."
    }
  ],
  "s15": [
    {
      "q": "The incidence of this condition is highest in which population?",
      "options": [
        "Primigravidas",
        "Multiparous women",
        "Women aged 35+ years",
        "Depends on the specific condition and risk factors"
      ],
      "correct": 3,
      "explain": "Incidence varies by condition — each has its own epidemiology and risk profile."
    },
    {
      "q": "When assessing this aspect, the most important factor is:",
      "options": [
        "Clinical correlation with patient presentation",
        "Laboratory confirmation",
        "Imaging evidence",
        "All of the above together"
      ],
      "correct": 3,
      "explain": "Assessment requires integration of clinical, laboratory, and imaging findings."
    },
    {
      "q": "The clinical significance of this section is:",
      "options": [
        "It guides management decisions",
        "It is primarily theoretical",
        "It applies only to research settings",
        "It has limited clinical utility"
      ],
      "correct": 0,
      "explain": "Understanding these concepts directly informs clinical management."
    },
    {
      "q": "Which of the following is a key concept?",
      "options": [
        "It is essential for understanding the condition",
        "It is rarely relevant in clinical practice",
        "It applies only to specific populations",
        "It has been replaced by newer classifications"
      ],
      "correct": 0,
      "explain": "Understanding key concepts is fundamental to clinical management."
    },
    {
      "q": "Which of the following best defines this condition?",
      "options": [
        "A pathological deviation from normal anatomy or function",
        "A condition requiring surgical intervention",
        "An incidental finding with no clinical significance",
        "A self-limiting disorder of pregnancy"
      ],
      "correct": 0,
      "explain": "A definition describes the essential nature of a condition as a deviation from normal."
    }
  ],
  "s16": [
    {
      "q": "Which of the following is a known risk factor?",
      "options": [
        "Maternal age above 35",
        "Multiparity",
        "Previous similar history",
        "All of the above may contribute depending on the condition"
      ],
      "correct": 3,
      "explain": "Multiple risk factors often contribute to obstetric conditions."
    },
    {
      "q": "The etiology of this condition involves:",
      "options": [
        "Genetic factors alone",
        "Environmental factors alone",
        "A complex interplay of genetic, environmental, and multifactorial elements",
        "Iatrogenic causes only"
      ],
      "correct": 2,
      "explain": "Most obstetric conditions have multifactorial etiology."
    },
    {
      "q": "In obstetric practice, this knowledge helps:",
      "options": [
        "Predict and prevent complications",
        "Diagnose conditions early",
        "Choose appropriate management",
        "All of the above"
      ],
      "correct": 3,
      "explain": "Comprehensive knowledge enables prevention, early diagnosis, and optimal management."
    },
    {
      "q": "Which of the following is a key concept?",
      "options": [
        "It is essential for understanding the condition",
        "It is rarely relevant in clinical practice",
        "It applies only to specific populations",
        "It has been replaced by newer classifications"
      ],
      "correct": 0,
      "explain": "Understanding key concepts is fundamental to clinical management."
    },
    {
      "q": "The clinical significance of this section is:",
      "options": [
        "It guides management decisions",
        "It is primarily theoretical",
        "It applies only to research settings",
        "It has limited clinical utility"
      ],
      "correct": 0,
      "explain": "Understanding these concepts directly informs clinical management."
    }
  ],
  "s17": [
    {
      "q": "Modifiable risk factors include:",
      "options": [
        "Smoking and obesity",
        "Age and parity",
        "Genetic predisposition",
        "None of the above"
      ],
      "correct": 0,
      "explain": "Smoking, obesity, and nutritional status are modifiable risk factors."
    },
    {
      "q": "Which of the following is a key concept?",
      "options": [
        "It is essential for understanding the condition",
        "It is rarely relevant in clinical practice",
        "It applies only to specific populations",
        "It has been replaced by newer classifications"
      ],
      "correct": 0,
      "explain": "Understanding key concepts is fundamental to clinical management."
    },
    {
      "q": "When assessing this aspect, the most important factor is:",
      "options": [
        "Clinical correlation with patient presentation",
        "Laboratory confirmation",
        "Imaging evidence",
        "All of the above together"
      ],
      "correct": 3,
      "explain": "Assessment requires integration of clinical, laboratory, and imaging findings."
    },
    {
      "q": "The clinical significance of this section is:",
      "options": [
        "It guides management decisions",
        "It is primarily theoretical",
        "It applies only to research settings",
        "It has limited clinical utility"
      ],
      "correct": 0,
      "explain": "Understanding these concepts directly informs clinical management."
    },
    {
      "q": "In obstetric practice, this knowledge helps:",
      "options": [
        "Predict and prevent complications",
        "Diagnose conditions early",
        "Choose appropriate management",
        "All of the above"
      ],
      "correct": 3,
      "explain": "Comprehensive knowledge enables prevention, early diagnosis, and optimal management."
    }
  ],
  "s18": [
    {
      "q": "When assessing this aspect, the most important factor is:",
      "options": [
        "Clinical correlation with patient presentation",
        "Laboratory confirmation",
        "Imaging evidence",
        "All of the above together"
      ],
      "correct": 3,
      "explain": "Assessment requires integration of clinical, laboratory, and imaging findings."
    },
    {
      "q": "The clinical significance of this section is:",
      "options": [
        "It guides management decisions",
        "It is primarily theoretical",
        "It applies only to research settings",
        "It has limited clinical utility"
      ],
      "correct": 0,
      "explain": "Understanding these concepts directly informs clinical management."
    },
    {
      "q": "The most common type is:",
      "options": [
        "Type 1 — mild form",
        "Type 2 — moderate form",
        "Type 3 — severe form",
        "Depends on the specific condition and classification system"
      ],
      "correct": 3,
      "explain": "Classification varies by condition — each has its own typing system."
    },
    {
      "q": "Which of the following is a key concept?",
      "options": [
        "It is essential for understanding the condition",
        "It is rarely relevant in clinical practice",
        "It applies only to specific populations",
        "It has been replaced by newer classifications"
      ],
      "correct": 0,
      "explain": "Understanding key concepts is fundamental to clinical management."
    },
    {
      "q": "In obstetric practice, this knowledge helps:",
      "options": [
        "Predict and prevent complications",
        "Diagnose conditions early",
        "Choose appropriate management",
        "All of the above"
      ],
      "correct": 3,
      "explain": "Comprehensive knowledge enables prevention, early diagnosis, and optimal management."
    }
  ],
  "s19": [
    {
      "q": "When assessing this aspect, the most important factor is:",
      "options": [
        "Clinical correlation with patient presentation",
        "Laboratory confirmation",
        "Imaging evidence",
        "All of the above together"
      ],
      "correct": 3,
      "explain": "Assessment requires integration of clinical, laboratory, and imaging findings."
    },
    {
      "q": "In obstetric practice, this knowledge helps:",
      "options": [
        "Predict and prevent complications",
        "Diagnose conditions early",
        "Choose appropriate management",
        "All of the above"
      ],
      "correct": 3,
      "explain": "Comprehensive knowledge enables prevention, early diagnosis, and optimal management."
    },
    {
      "q": "The most common presenting symptom is:",
      "options": [
        "Pain",
        "Abnormal bleeding",
        "Both pain and abnormal bleeding",
        "Depends on the specific condition"
      ],
      "correct": 3,
      "explain": "Clinical presentation varies — pain and bleeding are common but not universal symptoms."
    },
    {
      "q": "Which of the following is a key concept?",
      "options": [
        "It is essential for understanding the condition",
        "It is rarely relevant in clinical practice",
        "It applies only to specific populations",
        "It has been replaced by newer classifications"
      ],
      "correct": 0,
      "explain": "Understanding key concepts is fundamental to clinical management."
    },
    {
      "q": "Which sign on examination is characteristic?",
      "options": [
        "Abnormal vital signs",
        "Palpable abdominal mass",
        "Specific findings vary by condition",
        "None of the above"
      ],
      "correct": 2,
      "explain": "Examination findings depend heavily on the specific obstetric condition."
    }
  ],
  "s20": [
    {
      "q": "When assessing this aspect, the most important factor is:",
      "options": [
        "Clinical correlation with patient presentation",
        "Laboratory confirmation",
        "Imaging evidence",
        "All of the above together"
      ],
      "correct": 3,
      "explain": "Assessment requires integration of clinical, laboratory, and imaging findings."
    },
    {
      "q": "First-line management consists of:",
      "options": [
        "Immediate surgical intervention",
        "Conservative/medical management",
        "Referral to a specialist",
        "Depends on the specific condition and severity"
      ],
      "correct": 3,
      "explain": "Management approach varies — some conditions require surgery, others medical or conservative care."
    },
    {
      "q": "Which of the following is a key concept?",
      "options": [
        "It is essential for understanding the condition",
        "It is rarely relevant in clinical practice",
        "It applies only to specific populations",
        "It has been replaced by newer classifications"
      ],
      "correct": 0,
      "explain": "Understanding key concepts is fundamental to clinical management."
    },
    {
      "q": "In obstetric practice, this knowledge helps:",
      "options": [
        "Predict and prevent complications",
        "Diagnose conditions early",
        "Choose appropriate management",
        "All of the above"
      ],
      "correct": 3,
      "explain": "Comprehensive knowledge enables prevention, early diagnosis, and optimal management."
    },
    {
      "q": "The clinical significance of this section is:",
      "options": [
        "It guides management decisions",
        "It is primarily theoretical",
        "It applies only to research settings",
        "It has limited clinical utility"
      ],
      "correct": 0,
      "explain": "Understanding these concepts directly informs clinical management."
    }
  ],
  "s21": [
    {
      "q": "In obstetric practice, this knowledge helps:",
      "options": [
        "Predict and prevent complications",
        "Diagnose conditions early",
        "Choose appropriate management",
        "All of the above"
      ],
      "correct": 3,
      "explain": "Comprehensive knowledge enables prevention, early diagnosis, and optimal management."
    },
    {
      "q": "The incidence of this condition is highest in which population?",
      "options": [
        "Primigravidas",
        "Multiparous women",
        "Women aged 35+ years",
        "Depends on the specific condition and risk factors"
      ],
      "correct": 3,
      "explain": "Incidence varies by condition — each has its own epidemiology and risk profile."
    },
    {
      "q": "When assessing this aspect, the most important factor is:",
      "options": [
        "Clinical correlation with patient presentation",
        "Laboratory confirmation",
        "Imaging evidence",
        "All of the above together"
      ],
      "correct": 3,
      "explain": "Assessment requires integration of clinical, laboratory, and imaging findings."
    },
    {
      "q": "The gold standard diagnostic test is:",
      "options": [
        "Ultrasound imaging",
        "Laboratory blood tests",
        "Clinical examination alone",
        "Depends on the specific condition"
      ],
      "correct": 3,
      "explain": "The best diagnostic method varies by condition — some rely on imaging, others on lab tests or clinical findings."
    },
    {
      "q": "Which clinical finding is most suggestive of this diagnosis?",
      "options": [
        "Pain and bleeding",
        "Asymptomatic presentation",
        "Abnormal laboratory values",
        "Varies by condition — specific findings guide diagnosis"
      ],
      "correct": 3,
      "explain": "Clinical presentation differs by condition and guides diagnostic testing."
    }
  ],
  "s22": [
    {
      "q": "The clinical significance of this section is:",
      "options": [
        "It guides management decisions",
        "It is primarily theoretical",
        "It applies only to research settings",
        "It has limited clinical utility"
      ],
      "correct": 0,
      "explain": "Understanding these concepts directly informs clinical management."
    },
    {
      "q": "Which maternal characteristic increases risk?",
      "options": [
        "Advanced maternal age",
        "High parity",
        "Previous obstetric history",
        "All of the above"
      ],
      "correct": 3,
      "explain": "Multiple maternal factors contribute to obstetric risk."
    },
    {
      "q": "When assessing this aspect, the most important factor is:",
      "options": [
        "Clinical correlation with patient presentation",
        "Laboratory confirmation",
        "Imaging evidence",
        "All of the above together"
      ],
      "correct": 3,
      "explain": "Assessment requires integration of clinical, laboratory, and imaging findings."
    },
    {
      "q": "Which of the following is a key concept?",
      "options": [
        "It is essential for understanding the condition",
        "It is rarely relevant in clinical practice",
        "It applies only to specific populations",
        "It has been replaced by newer classifications"
      ],
      "correct": 0,
      "explain": "Understanding key concepts is fundamental to clinical management."
    },
    {
      "q": "Modifiable risk factors include:",
      "options": [
        "Smoking and obesity",
        "Age and parity",
        "Genetic predisposition",
        "None of the above"
      ],
      "correct": 0,
      "explain": "Smoking, obesity, and nutritional status are modifiable risk factors."
    }
  ],
  "s23": [
    {
      "q": "In obstetric practice, this knowledge helps:",
      "options": [
        "Predict and prevent complications",
        "Diagnose conditions early",
        "Choose appropriate management",
        "All of the above"
      ],
      "correct": 3,
      "explain": "Comprehensive knowledge enables prevention, early diagnosis, and optimal management."
    },
    {
      "q": "Which factor most influences the choice of treatment?",
      "options": [
        "Gestational age at presentation",
        "Maternal preference",
        "Facility resources",
        "All of the above — treatment is individualized"
      ],
      "correct": 3,
      "explain": "Obstetric management is tailored to gestational age, maternal status, and available resources."
    },
    {
      "q": "When assessing this aspect, the most important factor is:",
      "options": [
        "Clinical correlation with patient presentation",
        "Laboratory confirmation",
        "Imaging evidence",
        "All of the above together"
      ],
      "correct": 3,
      "explain": "Assessment requires integration of clinical, laboratory, and imaging findings."
    },
    {
      "q": "The clinical significance of this section is:",
      "options": [
        "It guides management decisions",
        "It is primarily theoretical",
        "It applies only to research settings",
        "It has limited clinical utility"
      ],
      "correct": 0,
      "explain": "Understanding these concepts directly informs clinical management."
    },
    {
      "q": "First-line management consists of:",
      "options": [
        "Immediate surgical intervention",
        "Conservative/medical management",
        "Referral to a specialist",
        "Depends on the specific condition and severity"
      ],
      "correct": 3,
      "explain": "Management approach varies — some conditions require surgery, others medical or conservative care."
    }
  ],
  "s24": [
    {
      "q": "In obstetric practice, this knowledge helps:",
      "options": [
        "Predict and prevent complications",
        "Diagnose conditions early",
        "Choose appropriate management",
        "All of the above"
      ],
      "correct": 3,
      "explain": "Comprehensive knowledge enables prevention, early diagnosis, and optimal management."
    },
    {
      "q": "The clinical significance of this section is:",
      "options": [
        "It guides management decisions",
        "It is primarily theoretical",
        "It applies only to research settings",
        "It has limited clinical utility"
      ],
      "correct": 0,
      "explain": "Understanding these concepts directly informs clinical management."
    },
    {
      "q": "Which of the following is a key concept?",
      "options": [
        "It is essential for understanding the condition",
        "It is rarely relevant in clinical practice",
        "It applies only to specific populations",
        "It has been replaced by newer classifications"
      ],
      "correct": 0,
      "explain": "Understanding key concepts is fundamental to clinical management."
    },
    {
      "q": "When assessing this aspect, the most important factor is:",
      "options": [
        "Clinical correlation with patient presentation",
        "Laboratory confirmation",
        "Imaging evidence",
        "All of the above together"
      ],
      "correct": 3,
      "explain": "Assessment requires integration of clinical, laboratory, and imaging findings."
    },
    {
      "q": "Which of the following is a key concept?",
      "options": [
        "It is essential for understanding the condition",
        "It is rarely relevant in clinical practice",
        "It applies only to specific populations",
        "It has been replaced by newer classifications"
      ],
      "correct": 0,
      "explain": "Understanding key concepts is fundamental to clinical management."
    }
  ],
  "s25": [
    {
      "q": "When assessing this aspect, the most important factor is:",
      "options": [
        "Clinical correlation with patient presentation",
        "Laboratory confirmation",
        "Imaging evidence",
        "All of the above together"
      ],
      "correct": 3,
      "explain": "Assessment requires integration of clinical, laboratory, and imaging findings."
    },
    {
      "q": "The clinical significance of this section is:",
      "options": [
        "It guides management decisions",
        "It is primarily theoretical",
        "It applies only to research settings",
        "It has limited clinical utility"
      ],
      "correct": 0,
      "explain": "Understanding these concepts directly informs clinical management."
    },
    {
      "q": "In obstetric practice, this knowledge helps:",
      "options": [
        "Predict and prevent complications",
        "Diagnose conditions early",
        "Choose appropriate management",
        "All of the above"
      ],
      "correct": 3,
      "explain": "Comprehensive knowledge enables prevention, early diagnosis, and optimal management."
    },
    {
      "q": "Which of the following is a key concept?",
      "options": [
        "It is essential for understanding the condition",
        "It is rarely relevant in clinical practice",
        "It applies only to specific populations",
        "It has been replaced by newer classifications"
      ],
      "correct": 0,
      "explain": "Understanding key concepts is fundamental to clinical management."
    },
    {
      "q": "Which of the following is a key concept?",
      "options": [
        "It is essential for understanding the condition",
        "It is rarely relevant in clinical practice",
        "It applies only to specific populations",
        "It has been replaced by newer classifications"
      ],
      "correct": 0,
      "explain": "Understanding key concepts is fundamental to clinical management."
    }
  ],
  "s26": [
    {
      "q": "Which of the following is a key concept?",
      "options": [
        "It is essential for understanding the condition",
        "It is rarely relevant in clinical practice",
        "It applies only to specific populations",
        "It has been replaced by newer classifications"
      ],
      "correct": 0,
      "explain": "Understanding key concepts is fundamental to clinical management."
    },
    {
      "q": "When assessing this aspect, the most important factor is:",
      "options": [
        "Clinical correlation with patient presentation",
        "Laboratory confirmation",
        "Imaging evidence",
        "All of the above together"
      ],
      "correct": 3,
      "explain": "Assessment requires integration of clinical, laboratory, and imaging findings."
    },
    {
      "q": "The clinical significance of this section is:",
      "options": [
        "It guides management decisions",
        "It is primarily theoretical",
        "It applies only to research settings",
        "It has limited clinical utility"
      ],
      "correct": 0,
      "explain": "Understanding these concepts directly informs clinical management."
    },
    {
      "q": "In obstetric practice, this knowledge helps:",
      "options": [
        "Predict and prevent complications",
        "Diagnose conditions early",
        "Choose appropriate management",
        "All of the above"
      ],
      "correct": 3,
      "explain": "Comprehensive knowledge enables prevention, early diagnosis, and optimal management."
    },
    {
      "q": "Which of the following is a key concept?",
      "options": [
        "It is essential for understanding the condition",
        "It is rarely relevant in clinical practice",
        "It applies only to specific populations",
        "It has been replaced by newer classifications"
      ],
      "correct": 0,
      "explain": "Understanding key concepts is fundamental to clinical management."
    }
  ]
}